shikimori_api/__init__.py
shikimori_api/shikimori_api.py
shikimori_api-1.0.1.dist-info/LICENSE
shikimori_api-1.0.1.dist-info/METADATA
shikimori_api-1.0.1.dist-info/WHEEL
shikimori_api-1.0.1.dist-info/top_level.txt
shikimori_api-1.0.1.dist-info/RECORD
