Metadata-Version: 2.1
Name: shikimori-api
Version: 1.0.1
Summary: Wrapper for Shikimori API
Home-page: https://github.com/nomnoms12/shikimori_api/
Author: nomnoms12
Author-email: alexander.ign0918@gmail.com
License: UNKNOWN
Project-URL: Bug Reports, https://github.com/nomnoms12/shikimori_api/issues/
Project-URL: Source, https://github.com/nomnoms12/shikimori_api/
Platform: UNKNOWN
Classifier: Programming Language :: Python :: 3.6
Classifier: Programming Language :: Python :: 3.7
Classifier: Programming Language :: Python :: 3.8
Classifier: License :: OSI Approved :: MIT License
Classifier: Operating System :: OS Independent
Requires-Python: >= 3.6
Requires-Dist: requests-oauthlib (~=1.3.0)
Provides-Extra: test
Requires-Dist: responses (~=0.10.14) ; extra == 'test'
Requires-Dist: pytest (~=5.4.2) ; extra == 'test'
Requires-Dist: pytest-cov (~=2.8.1) ; extra == 'test'
Requires-Dist: coveralls (~=2.0.0) ; extra == 'test'
